PyMieSim/__init__.py
PyMieSim/__main__.py
PyMieSim/_utils.py
PyMieSim/_version.py
PyMieSim/binary/__init__.py
PyMieSim/binary/interface_experiment.cp311-win_amd64.pyd
PyMieSim/binary/interface_experiment.cp312-win_amd64.pyd
PyMieSim/binary/interface_pint.cp311-win_amd64.pyd
PyMieSim/binary/interface_pint.cp312-win_amd64.pyd
PyMieSim/binary/interface_single.cp311-win_amd64.pyd
PyMieSim/binary/interface_single.cp312-win_amd64.pyd
PyMieSim/binary/interface_source.cp311-win_amd64.pyd
PyMieSim/binary/interface_source.cp312-win_amd64.pyd
PyMieSim/binary/libbase_scatterer.a
PyMieSim/binary/libbessel_subroutine.a
PyMieSim/binary/libcoordinates.a
PyMieSim/binary/libcoreshell.a
PyMieSim/binary/libcylinder.a
PyMieSim/binary/libfibonacci.a
PyMieSim/binary/libfull_mesh.a
PyMieSim/binary/libmode_field.a
PyMieSim/binary/libpint.a
PyMieSim/binary/libsource.a
PyMieSim/binary/libsphere.a
PyMieSim/directories.py
PyMieSim/experiment/__init__.py
PyMieSim/experiment/dataframe_subclass.py
PyMieSim/experiment/detector/__init__.py
PyMieSim/experiment/detector/base.py
PyMieSim/experiment/detector/coherent_mode.py
PyMieSim/experiment/detector/photodiode.py
PyMieSim/experiment/scatterer/__init__.py
PyMieSim/experiment/scatterer/base.py
PyMieSim/experiment/scatterer/core_shell.py
PyMieSim/experiment/scatterer/cylinder.py
PyMieSim/experiment/scatterer/sphere.py
PyMieSim/experiment/setup.py
PyMieSim/experiment/source/__init__.py
PyMieSim/experiment/source/base.py
PyMieSim/experiment/source/gaussian.py
PyMieSim/experiment/source/planewave.py
PyMieSim/experiment/utils.py
PyMieSim/gui/__init__.py
PyMieSim/gui/helper.py
PyMieSim/gui/interface.py
PyMieSim/gui/section_/__init__.py
PyMieSim/gui/section_/base.py
PyMieSim/gui/section_/detector.py
PyMieSim/gui/section_/measure.py
PyMieSim/gui/section_/scatterer.py
PyMieSim/gui/section_/source.py
PyMieSim/single/__init__.py
PyMieSim/single/detector/__init__.py
PyMieSim/single/mesh.py
PyMieSim/single/plottings.py
PyMieSim/single/polarization.py
pymiesim-4.0.2.dist-info/METADATA
pymiesim-4.0.2.dist-info/WHEEL
pymiesim-4.0.2.dist-info/licenses/LICENSE
pymiesim-4.0.2.dist-info/RECORD
