Metadata-Version: 2.2
Name: PyMieSim
Version: 4.0.2
Summary: A package for light scattering (Mie) computation.
Keywords: mie,scattering,backscatter,sphere,cylinder,nanoparticle,phase function,efficiency,rayleigh,backscattering
Author-Email: Martin Poinsinet de Sivry-Houle <martin.poinsinet.de.sivry@gmail.com>
License: MIT License
Classifier: Programming Language :: Python
Classifier: Programming Language :: Python :: 3
Classifier: Programming Language :: Python :: 3.10
Classifier: Programming Language :: Python :: 3.11
Classifier: Programming Language :: Python :: 3.12
Classifier: Programming Language :: Python :: 3.13
Classifier: Programming Language :: Python :: Implementation :: CPython
Classifier: Development Status :: 5 - Production/Stable
Classifier: Intended Audience :: Science/Research
Classifier: Intended Audience :: Developers
Classifier: Topic :: Scientific/Engineering :: Physics
Classifier: Topic :: Scientific/Engineering :: Mathematics
Classifier: Topic :: Scientific/Engineering :: Visualization
Classifier: Topic :: Software Development :: Libraries :: Python Modules
Classifier: License :: OSI Approved :: MIT License
Classifier: Operating System :: OS Independent
Classifier: Framework :: Jupyter
Classifier: Framework :: Sphinx
Project-URL: Documentation, https://martinpdes.github.io/PyMieSim/
Project-URL: Repository, https://github.com/MartinPdeS/PyMieSim
Requires-Python: >=3.10
Requires-Dist: TypedUnit
Requires-Dist: MPSPlots
Requires-Dist: PyOptik
Requires-Dist: setuptools_scm[toml]<10,>=8
Requires-Dist: numpy==2.2.6
Requires-Dist: matplotlib==3.10.8
Requires-Dist: pydantic<2.13.0,>=2.9.2
Requires-Dist: pint-pandas~=0.6
Requires-Dist: pandas~=2.3.0
Requires-Dist: tabulate~=0.9
Requires-Dist: pyvista==0.45.3
Provides-Extra: testing
Requires-Dist: pytest>=0.6; extra == "testing"
Requires-Dist: pytest-cov>=2.0; extra == "testing"
Requires-Dist: pytest-json-report==1.5.0; extra == "testing"
Requires-Dist: coverage==7.13.1; extra == "testing"
Provides-Extra: documentation
Requires-Dist: numpydoc==1.10.0; extra == "documentation"
Requires-Dist: sphinx>=5.1.1; extra == "documentation"
Requires-Dist: sphinx-rtd-theme==3.0.2; extra == "documentation"
Requires-Dist: sphinx-gallery==0.20.0; extra == "documentation"
Requires-Dist: sphinx_design==0.6.1; extra == "documentation"
Requires-Dist: pydata-sphinx-theme==0.16.1; extra == "documentation"
Provides-Extra: dev
Requires-Dist: flake8==7.3.0; extra == "dev"
